bloonspy/AsyncClient.py
bloonspy/Client.py
bloonspy/__init__.py
bloonspy/exceptions.py
bloonspy/model/Asset.py
bloonspy/model/Event.py
bloonspy/model/GameVersion.py
bloonspy/model/Loadable.py
bloonspy/model/__init__.py
bloonspy/model/btd6/Boss.py
bloonspy/model/btd6/Challenge.py
bloonspy/model/btd6/ContestedTerritory.py
bloonspy/model/btd6/Cosmetics.py
bloonspy/model/btd6/CustomMap.py
bloonspy/model/btd6/Gamemode.py
bloonspy/model/btd6/Map.py
bloonspy/model/btd6/Medals.py
bloonspy/model/btd6/Odyssey.py
bloonspy/model/btd6/Power.py
bloonspy/model/btd6/Progress.py
bloonspy/model/btd6/Race.py
bloonspy/model/btd6/Restriction.py
bloonspy/model/btd6/Rewards.py
bloonspy/model/btd6/Score.py
bloonspy/model/btd6/Team.py
bloonspy/model/btd6/Tower.py
bloonspy/model/btd6/User.py
bloonspy/model/btd6/UserSave.py
bloonspy/model/btd6/__init__.py
bloonspy/utils/Infinity.py
bloonspy/utils/__init__.py
bloonspy/utils/api.py
bloonspy/utils/asyncapi.py
bloonspy/utils/decorators.py
bloonspy/utils/dictionaries.py
bloonspy-0.10.0.dist-info/licenses/LICENSE
tests/__init__.py
tests/async/__init__.py
tests/async/test_boss_leaderboard.py
tests/async/test_challenge_browser.py
tests/async/test_challenge_creator.py
tests/async/test_ct_leaderboard.py
tests/async/test_fetch_odyssey.py
tests/async/test_fetch_user.py
tests/async/test_race_leaderboard.py
tests/async/test_team_owner.py
tests/async/test_usersave.py
tests/integration/__init__.py
tests/integration/test_boss_leaderboard.py
tests/integration/test_challenge_browser.py
tests/integration/test_challenge_creator.py
tests/integration/test_ct_leaderboard.py
tests/integration/test_fetch_odyssey.py
tests/integration/test_fetch_user.py
tests/integration/test_map_browser.py
tests/integration/test_race_leaderboard.py
tests/integration/test_team_owner.py
tests/integration/test_usersave.py
tests/unit/__init__.py
tests/unit/test_boss.py
tests/unit/test_challenge.py
tests/unit/test_ct.py
tests/unit/test_custom_map.py
tests/unit/test_odyssey.py
tests/unit/test_race.py
tests/unit/test_team.py
bloonspy-0.10.0.dist-info/METADATA
bloonspy-0.10.0.dist-info/WHEEL
bloonspy-0.10.0.dist-info/top_level.txt
bloonspy-0.10.0.dist-info/RECORD
