Metadata-Version: 2.4
Name: bloonspy
Version: 0.10.0
Summary: A Python wrapper for the Ninja Kiwi Open Data API
Home-page: https://github.com/SartoRiccardo/bloonspy
Author: SartoRiccardo
Classifier: Programming Language :: Python :: 3
Classifier: License :: OSI Approved :: MIT License
Classifier: Operating System :: OS Independent
Requires-Python: >=3.10
License-File: LICENSE
Dynamic: author
Dynamic: classifier
Dynamic: description
Dynamic: description-content-type
Dynamic: home-page
Dynamic: license-file
Dynamic: requires-python
Dynamic: summary
